reigashi/__init__.py
reigashi/tokenization_tools.py
reigashi-0.0.1.dist-info/METADATA
reigashi-0.0.1.dist-info/WHEEL
reigashi-0.0.1.dist-info/top_level.txt
reigashi-0.0.1.dist-info/RECORD
