Metadata-Version: 2.1
Name: reigashi
Version: 0.0.1
Summary: some utils
Home-page: https://github.com/amenota/reigashi
Author: amenota
Author-email: leizd@outlook.com
License: UNKNOWN
Platform: UNKNOWN
Classifier: Programming Language :: Python :: 3
Classifier: License :: OSI Approved :: MIT License
Classifier: Operating System :: OS Independent
Requires-Python: >=3.6
